taimos/cdk_construct_alexa_skill/__init__.py
taimos/cdk_construct_alexa_skill/py.typed
taimos/cdk_construct_alexa_skill/_jsii/__init__.py
taimos/cdk_construct_alexa_skill/_jsii/cdk-construct-alexa-skill@1.1.0.jsii.tgz
taimos.cdk_construct_alexa_skill-1.1.0.dist-info/METADATA
taimos.cdk_construct_alexa_skill-1.1.0.dist-info/WHEEL
taimos.cdk_construct_alexa_skill-1.1.0.dist-info/top_level.txt
taimos.cdk_construct_alexa_skill-1.1.0.dist-info/RECORD
