Metadata-Version: 2.1
Name: taimos.cdk-construct-alexa-skill
Version: 1.1.0
Summary: An AWS CDK Construct that creates an Alexa Skill backend
Home-page: https://github.com/taimos/cdk-construct-alexa-skill
Author: Thorsten Hoeger<thorsten.hoeger@taimos.de>
License: Apache-2.0
Project-URL: Source, https://github.com/taimos/cdk-construct-alexa-skill
Platform: UNKNOWN
Classifier: Intended Audience :: Developers
Classifier: Operating System :: OS Independent
Classifier: Programming Language :: JavaScript
Classifier: Programming Language :: Python :: 3 :: Only
Classifier: Programming Language :: Python :: 3.6
Classifier: Programming Language :: Python :: 3.7
Classifier: Programming Language :: Python :: 3.8
Classifier: Typing :: Typed
Classifier: License :: OSI Approved
Requires-Python: >=3.6
Requires-Dist: jsii (<2.0.0,>=1.9.0)
Requires-Dist: publication (>=0.0.3)
Requires-Dist: aws-cdk.aws-dynamodb (==1.54.0)
Requires-Dist: aws-cdk.aws-iam (==1.54.0)
Requires-Dist: aws-cdk.aws-lambda (==1.54.0)
Requires-Dist: aws-cdk.aws-s3 (==1.54.0)
Requires-Dist: aws-cdk.core (==1.54.0)
Requires-Dist: constructs (==3.0.4)
